olympiabhub/__init__.py
olympiabhub/api.py
tests/__init__.py
tests/test_api.py
Olympiabhub-1.0.0.dist-info/LICENSE
Olympiabhub-1.0.0.dist-info/METADATA
Olympiabhub-1.0.0.dist-info/WHEEL
Olympiabhub-1.0.0.dist-info/top_level.txt
Olympiabhub-1.0.0.dist-info/RECORD
