Metadata-Version: 2.1
Name: Olympiabhub
Version: 1.0.0
Summary: Librairie pour interagir avec l'API Olympia.
Home-page: https://github.com/nicolassaint/olympiabhub
Author: Bercy Hub
Author-email: nicolas.saint@finances.gouv.fr
Classifier: Programming Language :: Python :: 3
Classifier: License :: OSI Approved :: MIT License
Classifier: Operating System :: OS Independent
Requires-Python: >=3.6
License-File: LICENSE
Requires-Dist: requests
Requires-Dist: python-dotenv
